odoo/addons/mis_builder_budget_contrib/README.rst
odoo/addons/mis_builder_budget_contrib/__init__.py
odoo/addons/mis_builder_budget_contrib/__manifest__.py
odoo/addons/mis_builder_budget_contrib/i18n/mis_builder_budget_contrib.pot
odoo/addons/mis_builder_budget_contrib/models/__init__.py
odoo/addons/mis_builder_budget_contrib/models/mis_budget_by_account_item.py
odoo/addons/mis_builder_budget_contrib/readme/CONTRIBUTORS.rst
odoo/addons/mis_builder_budget_contrib/readme/DESCRIPTION.rst
odoo/addons/mis_builder_budget_contrib/readme/HISTORY.rst
odoo/addons/mis_builder_budget_contrib/readme/ROADMAP.rst
odoo/addons/mis_builder_budget_contrib/readme/USAGE.rst
odoo/addons/mis_builder_budget_contrib/readme/newsfragments/.gitignore
odoo/addons/mis_builder_budget_contrib/readme/newsfragments/32.feature
odoo/addons/mis_builder_budget_contrib/static/description/icon.png
odoo/addons/mis_builder_budget_contrib/static/description/index.html
odoo/addons/mis_builder_budget_contrib/views/mis_budget_by_account_item.xml
odoo_addon_mis_builder_budget_contrib-15.0.1.0.0.2.dist-info/METADATA
odoo_addon_mis_builder_budget_contrib-15.0.1.0.0.2.dist-info/WHEEL
odoo_addon_mis_builder_budget_contrib-15.0.1.0.0.2.dist-info/top_level.txt
odoo_addon_mis_builder_budget_contrib-15.0.1.0.0.2.dist-info/RECORD
